stepchain/__init__.py
stepchain/config.py
stepchain/errors.py
stepchain/function_registry.py
stepchain/cli/__init__.py
stepchain/cli/main.py
stepchain/core/__init__.py
stepchain/core/decomposer.py
stepchain/core/executor.py
stepchain/core/models.py
stepchain/core/scheduler.py
stepchain/integrations/__init__.py
stepchain/integrations/openai.py
stepchain/storage/__init__.py
stepchain/storage/jsonl.py
stepchain/utils/__init__.py
stepchain/utils/compression.py
stepchain/utils/logging.py
stepchain/utils/retry.py
stepchain/utils/telemetry.py
stepchain-0.3.1.dist-info/licenses/LICENSE
stepchain-0.3.1.dist-info/METADATA
stepchain-0.3.1.dist-info/WHEEL
stepchain-0.3.1.dist-info/entry_points.txt
stepchain-0.3.1.dist-info/top_level.txt
stepchain-0.3.1.dist-info/RECORD
