Metadata-Version: 2.4
Name: stepchain
Version: 0.3.1
Summary: The thinnest possible layer for reliable AI workflows - 185 lines, zero complexity
Author-email: TaskCrew Team <team@taskcrew.ai>
License-Expression: MIT
Keywords: openai,reliability,orchestration,llm,task-decomposition,response-api
Classifier: Development Status :: 3 - Alpha
Classifier: Intended Audience :: Developers
Classifier: Programming Language :: Python :: 3
Classifier: Programming Language :: Python :: 3.12
Requires-Python: >=3.12
License-File: LICENSE
Requires-Dist: pydantic>=2.0
Requires-Dist: rich>=13.0
Requires-Dist: pyyaml>=6.0
Requires-Dist: opentelemetry-sdk>=1.20
Requires-Dist: opentelemetry-exporter-otlp>=1.20
Requires-Dist: openai>=1.0
Requires-Dist: click>=8.0
Provides-Extra: dev
Requires-Dist: mypy>=1.0; extra == "dev"
Requires-Dist: ruff>=0.1; extra == "dev"
Requires-Dist: pytest>=7.4; extra == "dev"
Requires-Dist: pytest-asyncio>=0.21; extra == "dev"
Requires-Dist: pytest-mock>=3.11; extra == "dev"
Requires-Dist: pytest-cov>=4.1; extra == "dev"
Requires-Dist: black>=23.0; extra == "dev"
Requires-Dist: pre-commit>=3.0; extra == "dev"
Provides-Extra: test
Requires-Dist: pytest>=7.4; extra == "test"
Requires-Dist: pytest-asyncio>=0.21; extra == "test"
Requires-Dist: pytest-mock>=3.11; extra == "test"
Requires-Dist: pytest-cov>=4.1; extra == "test"
Dynamic: license-file
